Workbook

Sheet Income
A1: Source | B1: Jan | C1: Feb | D1: Mar | E1: Apr | F1: May | G1: Jun | H1: Total
A2: Product sales | B2: 12000 | C2: 13500 | D2: 12800 | E2: 14200 | F2: 15100 | G2: 16000 | H2: =SUM(B2:G2)
A3: Consulting | B3: 4000 | C3: 3500 | D3: 5200 | E3: 4800 | F3: 5000 | G3: 6100 | H3: =SUM(B3:G3)
A4: Subscriptions | B4: 1800 | C4: 1900 | D4: 2050 | E4: 2100 | F4: 2300 | G4: 2400 | H4: =SUM(B4:G4)
A5: Total income | B5: =SUM(B2:B4) | C5: =SUM(C2:C4) | D5: =SUM(D2:D4) | E5: =SUM(E2:E4) | F5: =SUM(F2:F4) | G5: =SUM(G2:G4) | H5: =SUM(H2:H4)

Sheet Expenses
A1: Category | B1: Jan | C1: Feb | D1: Mar | E1: Apr | F1: May | G1: Jun | H1: Total | I1: Tax (15%) | J1: Spend Level
A2: Rent | B2: 3000 | C2: 3000 | D2: 3000 | E2: 3000 | F2: 3000 | G2: 3000 | H2: =SUM(B2:G2) | I2: =H2*0.15 | J2: =IF(H2>10000,"High","Low")
A3: Payroll | B3: 8500 | C3: 8500 | D3: 9000 | E3: 9000 | F3: 9200 | G3: 9200 | H3: =SUM(B3:G3) | I3: =H3*0.15 | J3: =IF(H3>10000,"High","Low")
A4: Marketing | B4: 1200 | C4: 1500 | D4: 1100 | E4: 1800 | F4: 2000 | G4: 1700 | H4: =SUM(B4:G4) | I4: =H4*0.15 | J4: =IF(H4>10000,"High","Low")
A5: Software | B5: 450 | C5: 450 | D5: 480 | E5: 480 | F5: 500 | G5: 500 | H5: =SUM(B5:G5) | I5: =H5*0.15 | J5: =IF(H5>10000,"High","Low")
A6: Utilities | B6: 320 | C6: 300 | D6: 290 | E6: 280 | F6: 310 | G6: 330 | H6: =SUM(B6:G6) | I6: =H6*0.15 | J6: =IF(H6>10000,"High","Low")
A7: Total expenses | B7: =SUM(B2:B6) | C7: =SUM(C2:C6) | D7: =SUM(D2:D6) | E7: =SUM(E2:E6) | F7: =SUM(F2:F6) | G7: =SUM(G2:G6) | H7: =SUM(H2:H6) | I7: =SUM(I2:I6)

Sheet Summary
A1: Month | B1: Income | C1: Expenses | D1: Net Profit | E1: Margin
A2: Jan | B2: ='Income'!B5 | C2: ='Expenses'!B7 | D2: =B2-C2 | E2: =IFERROR(D2/B2,0)
A3: Feb | B3: ='Income'!C5 | C3: ='Expenses'!C7 | D3: =B3-C3 | E3: =IFERROR(D3/B3,0)
A4: Mar | B4: ='Income'!D5 | C4: ='Expenses'!D7 | D4: =B4-C4 | E4: =IFERROR(D4/B4,0)
A5: Apr | B5: ='Income'!E5 | C5: ='Expenses'!E7 | D5: =B5-C5 | E5: =IFERROR(D5/B5,0)
A6: May | B6: ='Income'!F5 | C6: ='Expenses'!F7 | D6: =B6-C6 | E6: =IFERROR(D6/B6,0)
A7: Jun | B7: ='Income'!G5 | C7: ='Expenses'!G7 | D7: =B7-C7 | E7: =IFERROR(D7/B7,0)
A8: Total | B8: =SUM(B2:B7) | C8: =SUM(C2:C7) | D8: =B8-C8 | E8: =IFERROR(D8/B8,0)
